{
  "collectionName": "components_header_sub_sections",
  "info": {
    "name": "subSection",
    "icon": "folder-open",
    "description": ""
  },
  "options": {},
  "attributes": {
    "label": {
      "type": "string",
      "required": true,
      "maxLength": 20
    },
    "href": {
      "type": "string",
      "required": true
    },
    "description": {
      "type": "text"
    },
    "icon": {
      "type": "enumeration",
      "enum": [
        "gavel",
        "group",
        "atlas",
        "colorlens",
        "car",
        "question",
        "university",
        "microphone",
        "beer",
        "work",
        "workshop"
      ],
      "default": "question",
      "required": true
    },
    "color": {
      "type": "enumeration",
      "enum": [
        "black",
        "white",
        "gray",
        "red",
        "orange",
        "yellow",
        "green",
        "teal",
        "blue",
        "cyan",
        "purple",
        "pink"
      ],
      "required": true,
      "default": "gray"
    }
  }
}
